bumpcalver/__init__.py
bumpcalver/backup_utils.py
bumpcalver/cli.py
bumpcalver/config.py
bumpcalver/git_utils.py
bumpcalver/handlers.py
bumpcalver/undo_utils.py
bumpcalver/utils.py
bumpcalver-2025.12.30.1.dist-info/METADATA
bumpcalver-2025.12.30.1.dist-info/WHEEL
bumpcalver-2025.12.30.1.dist-info/entry_points.txt
bumpcalver-2025.12.30.1.dist-info/licenses/LICENSE
bumpcalver-2025.12.30.1.dist-info/RECORD
