Metadata-Version: 2.4
Name: bumpcalver
Version: 2025.12.30.1
Summary: A CLI tool for calendar-based version bumping
Project-URL: Homepage, https://github.com/devsetgo/bumpcalver
Project-URL: Documentation, https://devsetgo.github.io/bumpcalver/
Project-URL: Repository, https://github.com/devsetgo/bumpcalver
Author-email: Mike Ryan <mikeryan56@gmail.com>
License: MIT License
License-File: LICENSE
Keywords: calendar versioning,calver,cli,library,python,versioning
Classifier: License :: OSI Approved :: MIT License
Classifier: Operating System :: MacOS :: MacOS X
Classifier: Operating System :: Microsoft :: Windows
Classifier: Operating System :: POSIX
Classifier: Operating System :: POSIX :: Linux
Classifier: Programming Language :: Python
Classifier: Programming Language :: Python :: 3
Classifier: Programming Language :: Python :: 3.9
Classifier: Programming Language :: Python :: 3.10
Classifier: Programming Language :: Python :: 3.11
Classifier: Programming Language :: Python :: 3.12
Classifier: Programming Language :: Python :: 3.13
Requires-Python: >=3.9
Requires-Dist: click>=8.0
Requires-Dist: pyyaml>=6.0.2
Requires-Dist: toml>=0.10.2
